EduRPA/__init__.py
EduRPA/Google/Classroom.py
EduRPA/Google/CustomOAuth.py
EduRPA/Google/Form.py
EduRPA/Google/Utils.py
EduRPA/Google/__init__.py
edurpa_google-1.1.1.dist-info/LICENSE
edurpa_google-1.1.1.dist-info/METADATA
edurpa_google-1.1.1.dist-info/WHEEL
edurpa_google-1.1.1.dist-info/top_level.txt
edurpa_google-1.1.1.dist-info/RECORD
