Metadata-Version: 2.1
Name: edurpa-google
Version: 1.1.1
Summary: Education Google RPA Librabry For Education
Home-page: https://github.com/edu-rpa/edurpa-google
Author: david
Author-email: davidhuynh0222@gmail.com
Classifier: Programming Language :: Python :: 2
Classifier: License :: OSI Approved :: MIT License
Classifier: Operating System :: OS Independent
License-File: LICENSE
Requires-Dist: robotframework (==6.1.1)
Requires-Dist: rpaframework (==27.7.0)
Requires-Dist: google-api-python-client
Requires-Dist: PyPDF2
Requires-Dist: gdown
